{"imagePath":"enemy_1507_mephi.png","SubTexture":[{"width":" 18","y":" 49","height":" 15","name":"Back_Hair","x":" 129"},{"y":" 76","x":" 224","width":" 17","height":" 22","name":"C_Sleeve_Cuff","rotated":"true"},{"width":" 48","y":" 205","height":" 17","name":"Eye_1","x":" 194"},{"y":" 47","x":" 59","width":" 48","height":" 12","name":"Eye_2","rotated":"true"},{"y":" 134","x":" 116","width":" 45","height":" 7","name":"Eyebrow","rotated":"true"},{"y":" 127","x":" 156","width":" 48","height":" 14","name":"Eyelash_1","rotated":"true"},{"y":" 174","x":" 244","width":" 48","height":" 10","name":"Eyelash_2","rotated":"true"},{"y":" 80","x":" 156","width":" 45","height":" 7","name":"Eyelash_3","rotated":"true"},{"y":" 177","x":" 127","width":" 28","height":" 43","name":"Front_Hair_A","rotated":"true"},{"width":" 23","y":" 2","height":" 39","name":"Front_Hair_B","x":" 2"},{"y":" 224","x":" 194","width":" 30","height":" 50","name":"Front_Hair_C","rotated":"true"},{"width":" 77","y":" 181","height":" 73","name":"Head","x":" 2"},{"y":" 85","x":" 99","width":" 18","height":" 24","name":"L_Arm","rotated":"true"},{"width":" 33","y":" 129","height":" 50","name":"L_Calf","x":" 23"},{"width":" 12","y":" 20","height":" 10","name":"L_Cheek","x":" 61"},{"width":" 29","y":" 121","height":" 18","name":"L_Foot","x":" 125"},{"width":" 29","y":" 92","height":" 27","name":"L_Forearm","x":" 125"},{"y":" 97","x":" 23","width":" 30","height":" 45","name":"L_Hair","rotated":"true"},{"width":" 22","y":" 81","height":" 23","name":"L_Hand_1","x":" 165"},{"width":" 26","y":" 102","height":" 17","name":"L_Hand_2_1","x":" 196"},{"width":" 12","y":" 185","height":" 18","name":"L_Hand_2_2","x":" 230"},{"y":" 2","x":" 27","width":" 16","height":" 11","name":"L_Hand_2_3","rotated":"true"},{"width":" 11","y":" 2","height":" 16","name":"L_Hand_2_4","x":" 40"},{"y":" 20","x":" 45","width":" 10","height":" 14","name":"L_Hand_2_5","rotated":"true"},{"width":" 8","y":" 225","height":" 13","name":"L_Hand_2_6","x":" 246"},{"width":" 29","y":" 141","height":" 34","name":"L_Leg","x":" 125"},{"y":" 85","x":" 215","width":" 15","height":" 7","name":"Mouth_1","rotated":"true"},{"width":" 4","y":" 179","height":" 4","name":"Mouth_2","x":" 230"},{"width":" 15","y":" 40","height":" 7","name":"Mouth_3","x":" 129"},{"y":" 126","x":" 172","width":" 37","height":" 22","name":"Pelvis","rotated":"true"},{"width":" 20","y":" 66","height":" 24","name":"R_Arm","x":" 129"},{"width":" 21","y":" 35","height":" 21","name":"R_Arm_2","x":" 73"},{"width":" 39","y":" 204","height":" 50","name":"R_Calf","x":" 81"},{"width":" 19","y":" 32","height":" 13","name":"R_Cheek","x":" 52"},{"width":" 16","y":" 20","height":" 17","name":"R_Ear","x":" 27"},{"width":" 33","y":" 64","height":" 19","name":"R_Foot","x":" 94"},{"width":" 27","y":" 98","height":" 30","name":"R_Forearm","x":" 70"},{"y":" 121","x":" 196","width":" 20","height":" 26","name":"R_Forearm_2","rotated":"true"},{"width":" 24","y":" 43","height":" 52","name":"R_Hair","x":" 2"},{"y":" 105","x":" 99","width":" 25","height":" 24","name":"R_Hand_1","rotated":"true"},{"width":" 24","y":" 81","height":" 19","name":"R_Hand_2","x":" 189"},{"y":" 165","x":" 172","width":" 40","height":" 17","name":"R_Hand_3","rotated":"true"},{"y":" 41","x":" 116","width":" 21","height":" 11","name":"R_Hand_3_2","rotated":"true"},{"y":" 5","x":" 82","width":" 13","height":" 10","name":"R_Hand_3_3","rotated":"true"},{"y":" 58","x":" 73","width":" 38","height":" 19","name":"R_Hand_4","rotated":"true"},{"width":" 28","y":" 95","height":" 17","name":"R_Hand_5","x":" 224"},{"y":" 3","x":" 53","width":" 15","height":" 11","name":"R_Hand_5_2","rotated":"true"},{"width":" 13","y":" 20","height":" 13","name":"R_Hand_5_3","x":" 75"},{"width":" 7","y":" 72","height":" 11","name":"R_Hand_5_4","x":" 215"},{"width":" 26","y":" 143","height":" 33","name":"R_Leg","x":" 196"},{"width":" 37","y":" 178","height":" 25","name":"Top_Hair","x":" 191"},{"width":" 34","y":" 207","height":" 47","name":"Waist","x":" 122"},{"width":" 34","y":" 207","height":" 47","name":"Waist_2","x":" 158"},{"y":" 51","x":" 28","width":" 44","height":" 29","name":"Waist_Belt","rotated":"true"},{"width":" 14","y":" 6","height":" 12","name":"Waist_Parts_A","x":" 66"},{"y":" 106","x":" 165","width":" 18","height":" 29","name":"Waist_Parts_B","rotated":"true"},{"width":" 29","y":" 130","height":" 49","name":"Waist_Parts_C","x":" 58"},{"width":" 8","y":" 240","height":" 14","name":"Waist_Parts_D","x":" 246"},{"width":" 25","y":" 132","height":" 47","name":"Waist_Parts_E","x":" 89"},{"width":" 19","y":" 97","height":" 82","name":"Weapon_A","x":" 2"},{"width":" 30","y":" 144","height":" 28","name":"Weapon_B","x":" 224"},{"width":" 18","y":" 40","height":" 22","name":"Weapon_C","x":" 96"},{"width":" 22","y":" 39","height":" 10","name":"Weapon_D","x":" 28"},{"y":" 114","x":" 224","width":" 28","height":" 30","name":"Weapon_E","rotated":"true"},{"y":" 181","x":" 81","width":" 21","height":" 44","name":"Weapon_F","rotated":"true"}]}