{"imagePath":"enemy_1008_ghost.png","SubTexture":[{"width":" 44","y":" 212","height":" 42","name":"Head","x":" 145"},{"width":" 57","y":" 202","height":" 52","name":"Helmet","x":" 86"},{"width":" 82","y":" 202","height":" 52","name":"Helmet_2","x":" 2"},{"y":" 224","x":" 191","width":" 30","height":" 43","name":"L_Arm","rotated":"true"},{"width":" 22","y":" 36","height":" 19","name":"L_Finger","x":" 36"},{"y":" 231","x":" 236","width":" 23","height":" 18","name":"L_Finger_A","rotated":"true"},{"width":" 23","y":" 150","height":" 19","name":"L_Finger_B","x":" 117"},{"y":" 57","x":" 36","width":" 32","height":" 26","name":"L_Foot","rotated":"true"},{"y":" 187","x":" 174","width":" 23","height":" 21","name":"L_Hand","rotated":"true"},{"width":" 32","y":" 120","height":" 80","name":"L_Leg","x":" 2"},{"y":" 91","x":" 36","width":" 54","height":" 30","name":"Masks","rotated":"true"},{"width":" 33","y":" 152","height":" 48","name":"R_Arm","x":" 82"},{"y":" 171","x":" 117","width":" 29","height":" 26","name":"R_Foot","rotated":"true"},{"width":" 27","y":" 182","height":" 28","name":"R_Hand","x":" 145"},{"width":" 31","y":" 5","height":" 35","name":"R_Hand_B","x":" 2"},{"width":" 32","y":" 42","height":" 76","name":"R_Leg","x":" 2"},{"width":" 44","y":" 147","height":" 53","name":"Waist","x":" 36"},{"width":" 18","y":" 216","height":" 13","name":"Wristband","x":" 236"}]}