{"imagePath":"enemy_1026_aghost.png","SubTexture":[{"width":" 50","y":" 186","height":" 29","name":"C_Flashlight","x":" 66"},{"width":" 62","y":" 190","height":" 64","name":"C_Head","x":" 2"},{"y":" 218","height":" 53","width":" 36","rotated":"true","name":"C_L_Arm","x":" 191"},{"y":" 217","height":" 66","width":" 37","rotated":"true","name":"C_L_Calf","x":" 66"},{"width":" 36","y":" 48","height":" 30","name":"C_L_Foot","x":" 38"},{"y":" 178","height":" 31","width":" 30","rotated":"true","name":"C_L_Hand","x":" 147"},{"width":" 36","y":" 193","height":" 23","name":"C_L_Kneepad","x":" 191"},{"width":" 32","y":" 138","height":" 46","name":"C_L_Thigh","x":" 93"},{"width":" 55","y":" 210","height":" 44","name":"C_Light","x":" 134"},{"width":" 38","y":" 142","height":" 42","name":"C_LightSource","x":" 53"},{"width":" 33","y":" 10","height":" 48","name":"C_R_Arm","x":" 2"},{"width":" 34","y":" 60","height":" 66","name":"C_R_Calf","x":" 2"},{"width":" 27","y":" 186","height":" 22","name":"C_R_Finger","x":" 118"},{"width":" 35","y":" 17","height":" 29","name":"C_R_Foot","x":" 37"},{"y":" 136","height":" 23","width":" 26","rotated":"true","name":"C_R_Hand","x":" 127"},{"y":" 182","height":" 25","width":" 34","rotated":"true","name":"C_R_Kneepad","x":" 229"},{"width":" 29","y":" 80","height":" 46","name":"C_R_Thigh","x":" 38"},{"width":" 49","y":" 128","height":" 60","name":"C_Waist","x":" 2"},{"y":" 164","height":" 15","width":" 20","rotated":"true","name":"C_Wristband","x":" 127"}]}